MANIFEST.in
README.md
prefixspan-cli
requirements.txt
setup.py
prefixspan/__init__.py
prefixspan/api.py
prefixspan/closed.py
prefixspan/frequent.py
prefixspan/generator.py
prefixspan/localtyping.py
prefixspan/prefixspan.py
prefixspan/topk.py
prefixspan.egg-info/PKG-INFO
prefixspan.egg-info/SOURCES.txt
prefixspan.egg-info/dependency_links.txt
prefixspan.egg-info/requires.txt
prefixspan.egg-info/top_level.txt