Metadata-Version: 2.1
Name: prefixspan
Version: 0.5.1
Summary: PrefixSpan, BIDE, and FEAT in Python 3
Home-page: https://github.com/chuanconggao/PrefixSpan-py
Author: Chuancong Gao
Author-email: chuancong@gmail.com
License: MIT
Download-URL: https://github.com/chuanconggao/PrefixSpan-py/tarball/0.5.1
Keywords: data-mining,pattern-mining
Platform: UNKNOWN
Classifier: Operating System :: OS Independent
Classifier: Programming Language :: Python
Classifier: Programming Language :: Python :: 3
Requires-Python: >= 3
